[
  {
    "id": "923b067d-2dd0-4d06-bae0-2f4ff045c9b2",
    "parentSessionId": "ses_concurrent",
    "childSessionId": "fake-ses-1",
    "agent": "builder",
    "status": "error",
    "createdAt": 1778024772309,
    "safetyCeilingMs": 1800000,
    "lastMessageCount": 0,
    "stablePollCount": 0,
    "lastMessageCountChangeAt": 1778024772309,
    "nestingDepth": 1,
    "executionMode": "sdk",
    "workingDirectory": "/Users/apple/Documents/coding-projects/hivemind-plugin-1",
    "queueKey": "agent:builder",
    "surface": "agent-delegation",
    "recoveryGuarantee": "resumable",
    "explicitCancellation": false,
    "completedAt": 1778024772309,
    "error": "Failed to send prompt to child session",
    "gracePeriodExpiresAt": 1778025372310
  },
  {
    "id": "2af57b00-cc76-4df1-835b-506d2dcc5285",
    "parentSessionId": "ses_concurrent",
    "childSessionId": "fake-ses-2",
    "agent": "researcher",
    "status": "error",
    "createdAt": 1778024772310,
    "safetyCeilingMs": 1800000,
    "lastMessageCount": 0,
    "stablePollCount": 0,
    "lastMessageCountChangeAt": 1778024772310,
    "nestingDepth": 1,
    "executionMode": "sdk",
    "workingDirectory": "/Users/apple/Documents/coding-projects/hivemind-plugin-1",
    "queueKey": "agent:researcher",
    "surface": "agent-delegation",
    "recoveryGuarantee": "resumable",
    "explicitCancellation": false,
    "completedAt": 1778024772311,
    "error": "Failed to send prompt to child session",
    "gracePeriodExpiresAt": 1778025372311
  }
]
