[
  {
    "id": "22c18afd-c3b2-476d-8922-4332a72b0dbf",
    "parentSessionId": "ses-parent-monitor-fail",
    "childSessionId": "child-prompt-fail-monitor",
    "agent": "builder",
    "status": "error",
    "createdAt": 1779618334489,
    "lastMessageCount": 0,
    "stablePollCount": 0,
    "lastMessageCountChangeAt": 1779618334489,
    "nestingDepth": 1,
    "executionMode": "sdk",
    "workingDirectory": "/Users/apple/hivemind-plugin-private",
    "queueKey": "agent:builder",
    "surface": "agent-delegation",
    "recoveryGuarantee": "resumable",
    "explicitCancellation": false,
    "completedAt": 1779618334489,
    "error": "Failed to send prompt to child session",
    "gracePeriodExpiresAt": 1779618934490
  }
]
