{
  "_schema": "session/v2",
  "sessionId": "ses_2da91ea42ffeJoPz6qK7MlpjVb",
  "semanticSessionId": "ses_2026-03-26T011603_implementation_unknown_ses_2da91ea42ffeJoPz6qK7MlpjVb",
  "sdkSessionId": "ses_2da91ea42ffeJoPz6qK7MlpjVb",
  "lineage": "hiveminder",
  "purposeClass": "implementation",
  "agent": "unknown",
  "created": "2026-03-25T18:16:03.963Z",
  "updated": "2026-03-25T18:16:03.967Z",
  "status": "active",
  "parentSessionId": null,
  "childSessionIds": [],
  "counters": {
    "userMessageCount": 0,
    "assistantOutputCount": 2,
    "toolCallCount": 0,
    "delegationCount": 0,
    "compactionCount": 0,
    "turnCount": 1
  },
  "turns": [
    {
      "turnNumber": 1,
      "timestamp": "2026-03-25T18:16:03.963Z",
      "agent": "unknown",
      "model": "unknown",
      "duration": null,
      "userMessage": "",
      "assistantContent": "## Wave 7 Phase 08 Gate: PASS\n\n| Check | Evidence | Status |\n|-------|----------|--------|\n| `npx tsc --noEmit` | zero errors | ✓ |\n| Config group tests | 26/26 pass | ✓ |\n| Full suite | 473 pass, 0 fail | ✓ |\n| `npm run build` | succeeds | ✓ |\n| Handoff artifact | exported | ✓ |\n\n**Progress:** 8/11 phases complete. Critical path: 01 → 03 → 05 → **09 next** → 11\n\nProceeding to Wave 8: Phase 09 (Tiered injection) — **critical path, second-highest risk**."
    }
  ],
  "events": [
    {
      "turnNumber": 1,
      "type": "assistant_output",
      "importance": "medium",
      "timestamp": "2026-03-25T18:16:03.963Z",
      "data": {
        "text": "## Wave 7 Phase 08 Gate: PASS\n\n| Check | Evidence | Status |\n|-------|----------|--------|\n| `npx tsc --noEmit` | zero errors | ✓ |\n| Config group tests | 26/26 pass | ✓ |\n| Full suite | 473 pass, 0 fail | ✓ |\n| `npm run build` | succeeds | ✓ |\n| Handoff artifact | exported | ✓ |\n\n**Progress:** 8/11 phases complete. Critical path: 01 → 03 → 05 → **09 next** → 11\n\nProceeding to Wave 8: Phase 09 (Tiered injection) — **critical path, second-highest risk**.",
        "actor": "unknown"
      }
    }
  ],
  "diagnostics": [
    {
      "timestamp": "2026-03-25T18:16:03.963Z",
      "level": "info",
      "message": "turn_complete agent=unknown text_len=457"
    }
  ]
}